crop_people_yolo_cli-1.4.0.dist-info/METADATA
crop_people_yolo_cli-1.4.0.dist-info/WHEEL
crop_people_yolo_cli-1.4.0.dist-info/entry_points.txt
crop_people_yolo_cli-1.4.0.dist-info/licenses/LICENSE.txt
crop_yolo_cli/__init__.py
crop_yolo_cli/commands/__init__.py
crop_yolo_cli/commands/multi.py
crop_yolo_cli/commands/single.py
crop_yolo_cli/core/__init__.py
crop_yolo_cli/core/base.py
crop_yolo_cli/main.py
crop_people_yolo_cli-1.4.0.dist-info/RECORD
