Metadata-Version: 2.1
Name: crop-people-yolo-cli
Version: 1.4.0
Summary: put yolov12m/n/x.pt in ~/.yolov12 and run
Author-Email: Tadeas Fort <tadeasfort@proton.me>
License: GPL-3.0
Requires-Python: >=3.11
Requires-Dist: ultralytics>=8.3.149
Requires-Dist: typer>=0.16.0
Requires-Dist: rich>=14.0.0
Requires-Dist: opencv-python>=4.11.0.86
Requires-Dist: click>=8.2.1
Requires-Dist: loguru>=0.7.3
Requires-Dist: prompt-toolkit>=3.0.0
